setup.py
pyadd/__init__.py
pyadd/pyadd.py
pyadd.egg-info/PKG-INFO
pyadd.egg-info/SOURCES.txt
pyadd.egg-info/dependency_links.txt
pyadd.egg-info/top_level.txt