Metadata-Version: 2.1
Name: pyadd
Version: 0.1.1
Summary: Add PyPi-based imports
Author: UPD
